pypomes_s3/__init__.py
pypomes_s3/aws_pomes.py
pypomes_s3/minio_client.py
pypomes_s3/minio_pomes.py
pypomes_s3/s3_common.py
pypomes_s3/s3_pomes.py
pypomes_s3-1.0.6.dist-info/METADATA
pypomes_s3-1.0.6.dist-info/WHEEL
pypomes_s3-1.0.6.dist-info/licenses/LICENSE
pypomes_s3-1.0.6.dist-info/RECORD
