Metadata-Version: 2.4
Name: pypomes_s3
Version: 1.0.6
Summary: A collection of Python pomes, penyeach (S3 storage modules)
Project-URL: Homepage, https://github.com/TheWiseCoder/PyPomes-S3
Project-URL: Bug Tracker, https://github.com/TheWiseCoder/PyPomes-S3/issues
Author-email: GT Nunes <wisecoder01@gmail.com>
License-File: LICENSE
Classifier: License :: OSI Approved :: MIT License
Classifier: Operating System :: OS Independent
Classifier: Programming Language :: Python :: 3
Requires-Python: >=3.14
Requires-Dist: pypomes-core>=2.9.4
Requires-Dist: unidecode>=1.4.0
